{
  "contestants": [
    {
      "name": "Player 1",
      "score": 0
    },
    {
      "name": "Player 2",
      "score": 0
    },
    {
      "name": "Player 3",
      "score": 0
    }
  ],
  "categories": [
    {
      "name": "Cinematic Cuisine: Food in Film",
      "questions": [
        {
          "clue": "In 'Ratatouille', Remy the rat dreams of becoming a chef in this European city.",
          "answer": "Paris",
          "value": 200,
          "daily_double": false,
          "type": "text"
        },
        {
          "clue": "This 1994 film features a famous scene where John Travolta's character orders a 'Royale with Cheese'.",
          "answer": "Pulp Fiction",
          "value": 400,
          "daily_double": false,
          "type": "text"
        },
        {
          "clue": "In 'Willy Wonka & the Chocolate Factory', this character falls into a chocolate river and is sucked up a pipe.",
          "answer": "Augustus Gloop",
          "value": 600,
          "daily_double": false,
          "type": "text"
        },
        {
          "clue": "The 2009 animated film 'Cloudy with a Chance of Meatballs' features this type of food falling from the sky.",
          "answer": "Various foods",
          "value": 800,
          "daily_double": false,
          "type": "text"
        },
        {
          "clue": "In 'Goodfellas', there's a detailed scene where Paulie slices this ingredient with a razor blade in prison.",
          "answer": "Garlic",
          "value": 1000,
          "daily_double": false,
          "type": "text"
        }
      ]
    },
    {
      "name": "World Capitals: From A to Z",
      "questions": [
        {
          "clue": "This city is known for its famous opera house and also for its diverse food scene, including seafood and multicultural cuisine.",
          "answer": "What is Sydney?",
          "value": 200,
          "daily_double": false,
          "type": "text"
        },
        {
          "clue": "Known as the 'City of Light,' this capital is also the setting for many classic films and a hub for fine dining.",
          "answer": "What is Paris?",
          "value": 400,
          "daily_double": false,
          "type": "text"
        },
        {
          "clue": "This capital city features the iconic Red Square and has been a backdrop for numerous spy movies.",
          "answer": "What is Moscow?",
          "value": 600,
          "daily_double": false,
          "type": "text"
        },
        {
          "clue": "In this capital, you can enjoy traditional sushi and it has been featured in films like 'Lost in Translation.'",
          "answer": "What is Tokyo?",
          "value": 800,
          "daily_double": false,
          "type": "text"
        },
        {
          "clue": "Known for its vibrant street food and the Oscar-winning film 'Slumdog Millionaire,' this capital is a bustling metropolis.",
          "answer": "What is Mumbai?",
          "value": 1000,
          "daily_double": false,
          "type": "text"
        }
      ]
    },
    {
      "name": "Classical Composers and Their Works",
      "questions": [
        {
          "clue": "This composer's 'Four Seasons' suite has been used in movies like 'A View to a Kill' and 'What Lies Beneath'.",
          "answer": "Antonio Vivaldi",
          "value": 200,
          "daily_double": false,
          "type": "text"
        },
        {
          "clue": "Often featured in food commercials, this composer's 'Eine kleine Nachtmusik' is a staple of classical music.",
          "answer": "Wolfgang Amadeus Mozart",
          "value": 400,
          "daily_double": false,
          "type": "text"
        },
        {
          "clue": "This composer wrote the 'Moonlight Sonata', a piece that has been featured in films like 'Immortal Beloved'.",
          "answer": "Ludwig van Beethoven",
          "value": 600,
          "daily_double": false,
          "type": "text"
        },
        {
          "clue": "The dramatic 'O Fortuna' from 'Carmina Burana' by this composer has become synonymous with epic movie trailers.",
          "answer": "Carl Orff",
          "value": 800,
          "daily_double": false,
          "type": "text"
        },
        {
          "clue": "Used in movies like 'The King's Speech', this composer's 'Symphony No. 7' was described by Wagner as 'the apotheosis of the dance'.",
          "answer": "Ludwig van Beethoven",
          "value": 1000,
          "daily_double": false,
          "type": "text"
        }
      ]
    },
    {
      "name": "The Science of Weather Phenomena",
      "questions": [
        {
          "clue": "This weather phenomenon is often depicted in disaster movies, swirling violently with winds exceeding 70 miles per hour.",
          "answer": "Tornado",
          "value": 200,
          "daily_double": false,
          "type": "text"
        },
        {
          "clue": "This atmospheric phenomenon creates a brilliant arc of colors and is often seen after rain showers when sunlight shines through water droplets.",
          "answer": "Rainbow",
          "value": 400,
          "daily_double": false,
          "type": "text"
        },
        {
          "clue": "Known for its role in the 2004 movie 'The Day After Tomorrow', this current of fast-moving air influences weather patterns across the globe.",
          "answer": "Jet stream",
          "value": 600,
          "daily_double": false,
          "type": "text"
        },
        {
          "clue": "Named after a Spanish word, this weather phenomenon can lead to warmer ocean temperatures and is often associated with influencing global food supply.",
          "answer": "El Ni\u00f1o",
          "value": 800,
          "daily_double": false,
          "type": "text"
        },
        {
          "clue": "This weather condition, caused by the rapid cooling of Earth's surface, is known to create dangerous road conditions and is named after a type of frozen dessert.",
          "answer": "Black ice",
          "value": 1000,
          "daily_double": false,
          "type": "text"
        }
      ]
    },
    {
      "name": "Famous Art Heists in History",
      "questions": [
        {
          "clue": "In 1911, this famous artwork by Leonardo da Vinci was stolen from the Louvre, inspiring many films and books.",
          "answer": "Mona Lisa",
          "value": 200,
          "daily_double": false,
          "type": "text"
        },
        {
          "clue": "In 1990, two men dressed as police officers stole 13 pieces of art from this Boston museum, including works by Vermeer and Rembrandt.",
          "answer": "Isabella Stewart Gardner Museum",
          "value": 400,
          "daily_double": false,
          "type": "text"
        },
        {
          "clue": "In a 2003 heist, two paintings by Van Gogh were stolen from this Dutch museum named after the artist.",
          "answer": "Van Gogh Museum",
          "value": 600,
          "daily_double": false,
          "type": "text"
        },
        {
          "clue": "In 2000, a heist at the National Gallery in Oslo saw the theft of this Edvard Munch masterpiece, which was later recovered.",
          "answer": "The Scream",
          "value": 800,
          "daily_double": false,
          "type": "text"
        },
        {
          "clue": "In 2004, two paintings, including a Raphael, were stolen from this Scottish gallery during a daylight raid.",
          "answer": "Kelvingrove Art Gallery",
          "value": 1000,
          "daily_double": false,
          "type": "text"
        }
      ]
    }
  ],
  "final": {
    "category": "Famous Movie Meals",
    "clue": "This 1994 film features a pivotal scene in which a character discusses the regional names of a fast-food item, including \"Royale with Cheese\".",
    "answer": "What is Pulp Fiction?"
  }
}